[
  {
    "id": "pratik_001",
    "title": {
      "tr": "Kuzuma Enerji Veren Şirin Muz Ezmesi",
      "en": "Fork-Mashed Banana"
    },
    "description": {
      "tr": "Dışarıdayken veya acil durumlarda saniyeler içinde hazırlayabileceğiniz, muzun en doğal ve lezzetli hali.",
      "en": "The most natural and delicious form of banana that you can prepare in seconds while outdoors or in emergencies."
    },
    "category": 13,
    "ingredients": [
      {
        "amount": 1,
        "unit": {
          "tr": "adet",
          "en": "pcs"
        },
        "baseName": {
          "tr": "muz",
          "en": "banana"
        },
        "shoppingLabel": {
          "tr": "Muz",
          "en": "Banana"
        }
      }
    ],
    "preparationTime": 2,
    "calories": 90,
    "suitableAgeInMonths": 6,
    "allergicIngredients": [],
    "instructions": [
      {
        "tr": "Bal gibi tatlı muzumuzu soyup temiz ve şirin bir tabağa sevgiyle alalım.",
        "en": "Peel the banana and place it on a clean plate."
      },
      {
        "tr": "Çatalın arkasıyla minişimizin narin diline layık, pürüzsüz bir kıvam alana kadar tatlı tatlı ezip yedirelim.",
        "en": "Mash with the back of a fork until smooth and feed your baby."
      }
    ],
    "imageUrl": ""
  },
  {
    "id": "pratik_002",
    "title": {
      "tr": "Miniğin Avucuna Özel Yumuşacık Olgun Avokado",
      "en": "Avocado Wedges"
    },
    "description": {
      "tr":Sağlıklı yağlar içeren avokadonun, pişirme gerektirmeden dilimlenerek bebişin eline verilen en hızlı BLW atıştırmalığı.",
      "en": "The fastest BLW snack requiring no cooking, where healthy fat-rich avocado is sliced and handed to the baby."
    },
    "category": 13,
    "ingredients": [
      {
        "amount": 0.5,
        "unit": {
          "tr": "adet",
          "en": "pcs"
        },
        "baseName": {
          "tr": "olgun avokado",
          "en": "ripe avocado"
        },
        "shoppingLabel": {
          "tr": "Avokado",
          "en": "Avocado"
        }
      }
    ],
    "preparationTime": 2,
    "calories": 110,
    "suitableAgeInMonths": 7,
    "allergicIngredients": [],
    "instructions": [
      {
        "tr": "Tam kıvamında olgunlaşmış avokadomuzu ortadan ikiye bölüp çekirdeğini narince çıkaralım.",
        "en": "Cut a ripe avocado in half and gently remove its pit."
      },
      {
        "tr": "Kuzumuzun o minik parmaklarıyla kolayca kavrayabileceği, elinden kaymayacak şirin dilimler halinde kesip avucuna teslim edelim.",
        "en": "Cut it into segments that are easy for your baby to grasp and serve."
      }
    ],
    "imageUrl": ""
  },
  {
    "id": "pratik_003",
    "title": {
      "tr": "Saniyeler İçinde Hazır Yoğurtlu Ceviz Rüyası",
      "en": "Yogurt with Walnuts"
    },
    "description": {
      "tr": "Ev yoğurduna incecik çekilmiş ceviz karıştırılarak saniyeler içinde hazırlanan, besleyici ve pratik bir ikindi kasesi.",
      "en": "A nutritious and practical afternoon bowl prepared in seconds by mixing finely ground walnuts into homemade yogurt."
    },
    "category": 13,
    "ingredients": [
      {
        "amount": 3,
        "unit": {
          "tr": "yemek kaşığı",
          "en": "tbsp"
        },
        "baseName": {
          "tr": "ev yoğurdu",
          "en": "homemade yogurt"
        },
        "shoppingLabel": {
          "tr": "Yoğurt",
          "en": "Yogurt"
        }
      },
      {
        "amount": 1,
        "unit": {
          "tr": "tatlı kaşığı",
          "en": "tsp"
        },
        "baseName": {
          "tr": "un gibi çekilmiş ceviz",
          "en": "finely ground walnuts"
        },
        "shoppingLabel": {
          "tr": "Ceviz",
          "en": "Walnut"
        }
      }
    ],
    "preparationTime": 2,
    "calories": 85,
    "suitableAgeInMonths": 9,
    "allergicIngredients": [
      {
        "tr": "süt",
        "en": "milk"
      },
      {
        "tr": "ceviz",
        "en": "walnut"
      }
    ],
    "instructions": [
      {
        "tr": "Oda sıcaklığına getirdiğimiz mis kokulu ev yoğurdumuzu şirin bir kaseye anne şefkatiyle alalım.",
        "en": "Place room-temperature homemade yogurt in a small bowl."
      },
      {
        "tr": "İçine un gibi incecik çekilmiş, kuzumuzun boğazına kaçmayacak şifa kaynağı cevizimizi ekleyip neşeyle karıştıralım.",
        "en": "Add finely ground walnuts to the yogurt and stir well."
      }
    ],
    "imageUrl": ""
  },
  {
    "id": "pratik_004",
    "title": {
      "tr": "Bal Küpüne Tatlı Kayısı Sürprizi",
      "en": "Soaked Dried Apricot"
    },
    "description": {
      "tr": "Sıcak suda saniyeler içinde yumuşayan gün kurusu kayısının ezilmesiyle hazırlanan, bağırsak dostu tatlı bir ara öğün.",
      "en": "A bowel-friendly sweet snack prepared by mashing sun-dried apricots that soften in hot water in seconds."
    },
    "category": 13,
    "ingredients": [
      {
        "amount": 2,
        "unit": {
          "tr": "adet",
          "en": "pcs"
        },
        "baseName": {
          "tr": "gün kurusu kayısı",
          "en": "dried apricot"
        },
        "shoppingLabel": {
          "tr": "Kayısı",
          "en": "Apricot"
        }
      }
    ],
    "preparationTime": 5,
    "calories": 40,
    "suitableAgeInMonths": 7,
    "allergicIngredients": [],
    "instructions": [
      {
        "tr": "Kan deposu gün kurusu kayısılarımızı sıcak suya bırakıp, pamuk gibi yumuşayana kadar birkaç dakikacık keyifle bekletelim.",
        "en": "Soak dried apricots in hot water for a few minutes until soft."
      },
      {
        "tr": "Yumuşacık olan kayısıları sudan alıp çatalla narince ezelim, minişimizin yutması kolay olsun diye pürüzsüz bir püre kıvamına getirelim.",
        "en": "Remove the soft apricots from water and mash with a fork to a puree consistency."
      }
    ],
    "imageUrl": ""
  },
  {
    "id": "pratik_005",
    "title": {
      "tr": "Güne Güçlü Başlayan Minişlere Labneli Avokado",
      "en": "Avocado with Labneh"
    },
    "description": {
      "tr": "Çatalla ezilmiş avokado ve kremamsı labne peynirinin karıştırılmasıyla oluşan, pişirme gerektirmeyen besleyici kahvaltı sosu.",
      "en": "A nutritious, no-cook breakfast spread made by mixing mashed avocado and creamy labneh cheese."
    },
    "category": 13,
    "ingredients": [
      {
        "amount": 0.25,
        "unit": {
          "tr": "adet",
          "en": "pcs"
        },
        "baseName": {
          "tr": "avokado",
          "en": "avocado"
        },
        "shoppingLabel": {
          "tr": "Avokado",
          "en": "Avocado"
        }
      },
      {
        "amount": 1,
        "unit": {
          "tr": "yemek kaşığı",
          "en": "tbsp"
        },
        "baseName": {
          "tr": "bebek labnesi (tuzsuz)",
          "en": "baby labneh (unsalted)"
        },
        "shoppingLabel": {
          "tr": "Labne",
          "en": "Labneh"
        }
      }
    ],
    "preparationTime": 3,
    "calories": 80,
    "suitableAgeInMonths": 7,
    "allergicIngredients": [
      {
        "tr": "süt",
        "en": "milk"
      }
    ],
    "instructions": [
      {
        "tr": "Olgun avokadomuzu tabakta çatalla pürüzsüz olana dek anne özeniyle ezelim.",
        "en": "Mash the ripe avocado on a plate with a fork until smooth."
      },
      {
        "tr": "Üzerine kuzumuza özel o mis kokulu tuzsuz labnesini ekleyip, ipeksi bir kahvaltılık krema olana kadar tatlı tatlı harmanlayalım.",
        "en": "Add unsalted baby labneh and mix until it forms a smooth breakfast cream."
      }
    ],
    "imageUrl": ""
  },
  {
    "id": "pratik_006",
    "title": {
      "tr": "Minişlerin Lokmalık Peynirli Ekmek İçi",
      "en": "Breadcrumbs with Cheese"
    },
    "description": {
      "tr": "Yumuşak ekmek içinin lor peyniri ve zeytinyağı ile ıslatılmasıyla hazırlanan, bebişlerin parmaklarıyla yiyebileceği pratik lokmalar.",
      "en": "Quick bites prepared by moistening soft breadcrumbs with curd cheese and olive oil, perfect for baby's fingers."
    },
    "category": 13,
    "ingredients": [
      {
        "amount": 1,
        "unit": {
          "tr": "dilim",
          "en": "slice"
        },
        "baseName": {
          "tr": "ekmek içi (yumuşak)",
          "en": "breadcrumbs (soft)"
        },
        "shoppingLabel": {
          "tr": "Ekmek",
          "en": "Bread"
        }
      },
      {
        "amount": 1,
        "unit": {
          "tr": "yemek kaşığı",
          "en": "tbsp"
        },
        "baseName": {
          "tr": "tuzsuz lor peyniri",
          "en": "unsalted curd cheese"
        },
        "shoppingLabel": {
          "tr": "Lor Peyniri",
          "en": "Curd Cheese"
        }
      }
    ],
    "preparationTime": 3,
    "calories": 110,
    "suitableAgeInMonths": 9,
    "allergicIngredients": [
      {
        "tr": "buğday",
        "en": "wheat"
      },
      {
        "tr": "süt",
        "en": "milk"
      }
    ],
    "instructions": [
      {
        "tr": "Taze ekmeğimizin o yumuşacık içini minişimizin parmaklarına layık küçük parçalara ufalayalım.",
        "en": "Crumble the soft inside of fresh bread into tiny pieces."
      },
      {
        "tr": "Ufalanan ekmekleri tuzsuz lor peyniri ve şifa niyetine birkaç damla sızma zeytinyağı ile nemlendirip, kuzumuza lokma lokman sunalım.",
        "en": "Mix with unsalted curd cheese and a few drops of olive oil, then serve as tiny bites."
      }
    ],
    "imageUrl": ""
  },
  {
    "id": "pratik_007",
    "title": {
      "tr": "Akıllı Bıdıklara Pekmezli Gurme Yoğurt",
      "en": "Yogurt with Molasses"
    },
    "description": {
      "tr": "Ek gıda saatlerinde can kurtaran, taze ev yoğurdunun pekmezle tatlandırılmış en hızlı ve tatlı hali.",
      "en": "A lifesaver during snack times, featuring fresh homemade yogurt sweetened quickly with a touch of molasses."
    },
    "category": 13,
    "ingredients": [
      {
        "amount": 1,
        "unit": {
          "tr": "kase",
          "en": "bowl"
        },
        "baseName": {
          "tr": "ev yoğurdu",
          "en": "homemade yogurt"
        },
        "shoppingLabel": {
          "tr": "Yoğurt",
          "en": "Yogurt"
        }
      },
      {
        "amount": 1,
        "unit": {
          "tr": "tatlı kaşığı",
          "en": "tsp"
        },
        "baseName": {
          "tr": "üzüm pekmezi",
          "en": "grape molasses"
        },
        "shoppingLabel": {
          "tr": "Pekmez",
          "en": "Molasses"
        }
      }
    ],
    "preparationTime": 1,
    "calories": 75,
    "suitableAgeInMonths": 8,
    "allergicIngredients": [
      {
        "tr": "süt",
        "en": "milk"
      }
    ],
    "instructions": [
      {
        "tr": "Kalsiyum deposu ev yoğurdumuzu minişimizin kasesine güzelce paylaştıralım.",
        "en": "Scoop fresh homemade yogurt into your baby's bowl."
      },
      {
        "tr": "Üzerine kan yapıcı, şifa kaynağı üzüm pekmezimizi gezdirip, ebru sanatı gibi tatlı sarmallar oluşturarak karıştırıp yedirelim.",
        "en": "Drizzle grape molasses on top and mix gently before feeding."
      }
    ],
    "imageUrl": ""
  },
  {
    "id": "pratik_008",
    "title": {
      "tr": "Minişe Güç Veren Zeytinyağlı Lor Ezmesi",
      "en": "Mashed Curd with Olive Oil"
    },
    "description": {
      "tr": "Tuzsuz lor peynirinin halis zeytinyağı ile ezilerek saniyeler içinde yumuşacık bir kıvama getirildiği pratik kahvaltılık.",
      "en": "A quick breakfast dish where unsalted curd cheese is mashed with olive oil into a soft texture within seconds."
    },
    "category": 13,
    "ingredients": [
      {
        "amount": 2,
        "unit": {
          "tr": "yemek kaşığı",
          "en": "tbsp"
        },
        "baseName": {
          "tr": "lor peyniri",
          "en": "curd cheese"
        },
        "shoppingLabel": {
          "tr": "Peynir",
          "en": "Cheese"
        }
      },
      {
        "amount": 1,
        "unit": {
          "tr": "tatlı kaşığı",
          "en": "tsp"
        },
        "baseName": {
          "tr": "sızma zeytinyağı",
          "en": "olive oil"
        },
        "shoppingLabel": {
          "tr": "Zeytinyağı",
          "en": "Olive Oil"
        }
      }
    ],
    "preparationTime": 2,
    "calories": 70,
    "suitableAgeInMonths": 7,
    "allergicIngredients": [
      {
        "tr": "süt",
        "en": "milk"
      }
    ],
    "instructions": [
      {
        "tr": "Kuzumuz için hazırladığımız o yumuşacık, tuzsuz lor peynirini kahvaltı tabağına alalım.",
        "en": "Place unsalted curd cheese on a breakfast plate."
      },
      {
        "tr": "Üzerine halis sızma zeytinyağını gezdirip çatalla tatlı tatlı ezerek, bebişimizin damağında eriyecek ipeksi bir kıvam yakalayalım.",
        "en": "Drizzle extra virgin olive oil and mash with a fork until it reaches a smooth, spreadable consistency."
      }
    ],
    "imageUrl": ""
  },
  {
    "id": "pratik_009",
    "title": {
      "tr": "Yaz Güneşi Domates Sulu Ekmek Aşı",
      "en": "Breadcrumbs in Tomato Juice"
    },
    "description": {
      "tr": "Mevsiminde rendelenmiş domatesin suyu ile yumuşatılan ekmek içlerinden oluşan, pişirme gerektirmeyen çok pratik bir yaz öğünü.",
      "en": "A highly practical, no-cook summer dish consisting of breadcrumbs softened in fresh seasonal tomato juice."
    },
    "category": 13,
    "ingredients": [
      {
        "amount": 1,
        "unit": {
          "tr": "adet",
          "en": "pcs"
        },
        "baseName": {
          "tr": "tatlı yaz domatesi",
          "en": "sweet summer tomato"
        },
        "shoppingLabel": {
          "tr": "Domates",
          "en": "Tomato"
        }
      },
      {
        "amount": 1,
        "unit": {
          "tr": "dilim",
          "en": "slice"
        },
        "baseName": {
          "tr": "ekmek içi",
          "en": "breadcrumbs"
        },
        "shoppingLabel": {
          "tr": "Ekmek",
          "en": "Bread"
        }
      }
    ],
    "preparationTime": 5,
    "calories": 85,
    "suitableAgeInMonths": 10,
    "allergicIngredients": [
      {
        "tr": "domates",
        "en": "tomato"
      },
      {
        "tr": "buğday",
        "en": "wheat"
      }
    ],
    "instructions": [
      {
        "tr": "Yaz güneşiyle olgunlaşmış domatesimizi cam rendede anne özeniyle rendeleyip o şifalı, taze suyunu çıkaralım.",
        "en": "Grate a sweet summer tomato using a glass grater to collect its fresh juice."
      },
      {
        "tr": "Ekmek içlerimizi bu taze domates suyuyla buluşturup pamuk gibi yumuşamasını sağlayarak bal küpümüze keyifle yedirelim.",
        "en": "Soak breadcrumbs in this tomato juice, let them soften, and feed."
      }
    ],
    "imageUrl": ""
  },
  {
    "id": "pratik_010",
    "title": {
      "tr": "Geleneksel ve Hızlı Yoğurtlu Bisküvi Lapası",
      "en": "Milky Biscuits"
    },
    "description": {
      "tr": "Sütte yumuşatılmış bebe bisküvisinin pürüzsüz dokusuyla hazırlanan geleneksel ve hızlı ara öğün.",
      "en": "A traditional and quick snack prepared with the smooth texture of baby biscuits softened in milk."
    },
    "category": 13,
    "ingredients": [
      {
        "amount": 3,
        "unit": {
          "tr": "adet",
          "en": "pcs"
        },
        "baseName": {
          "tr": "bebe bisküvisi",
          "en": "baby biscuits"
        },
        "shoppingLabel": null
      }
    ],
    "preparationTime": 2,
    "calories": 120,
    "suitableAgeInMonths": 12,
    "allergicIngredients": [
      {
        "tr": "süt",
        "en": "milk"
      },
      {
        "tr": "buğday",
        "en": "wheat"
      }
    ],
    "instructions": [
      {
        "tr": "Ev yapımı mis kokulu bebe bisküvilerini tabağa alıp, üzerini geçecek kadar ılık süt ekleyerek pamuk gibi yumuşatalım.",
        "en": "Place baby biscuits in a bowl and soften them by soaking in warm milk."
      },
      {
        "tr": "Çatalla hafifçe bastırarak saniyeler içinde pürüzsüz bir lapa haline getirelim and bebişimize afiyetle yedirelim. Şifa olsun meleğimize!",
        "en": "Mash gently into a smooth paste and serve immediately."
      }
    ],
    "imageUrl": ""
  }
]
