[
  {
    "id": "sindirim_001",
    "title": {
      "tr": "Kabızlık Düşmanı Lifli Kabak Püresi",
      "en": "Fibrous Zucchini Puree"
    },
    "description": {
      "tr": "Yüksek lifli yapısıyla kabızlığı önleyen, kabak ve soğuk sıkım zeytinyağının bağırsak dostu uyumu.",
      "en": "A bowel-friendly harmony of zucchini and cold-pressed olive oil that prevents constipation with its high fiber."
    },
    "category": 15,
    "ingredients": [
      {
        "amount": 1,
        "unit": {
          "tr": "adet",
          "en": "pcs"
        },
        "baseName": {
          "tr": "kabak",
          "en": "zucchini"
        },
        "shoppingLabel": {
          "tr": "Kabak",
          "en": "Zucchini"
        }
      },
      {
        "amount": 1,
        "unit": {
          "tr": "tatlı kaşığı",
          "en": "tsp"
        },
        "baseName": {
          "tr": "zeytinyağı",
          "en": "olive oil"
        },
        "shoppingLabel": {
          "tr": "Zeytinyağı",
          "en": "Olive Oil"
        }
      }
    ],
    "preparationTime": 15,
    "calories": 45,
    "suitableAgeInMonths": 6,
    "allergicIngredients": [],
    "instructions": [
      {
        "tr": "Taptaze kabağımızı buharda, miniğimizin yutabileceği şekilde lokum gibi yumuşayana kadar güzelce pişirelim.",
        "en": "Steam the zucchini until soft."
      },
      {
        "tr": "Henüz sıcakken çatalla bir güzel ezelim, içine şifa niyetine bol zeytinyağı gezdirip bebişimize ılık ılık yedirelim. Yarasın kuzumuza!",
        "en": "Mash with a fork while hot, add a generous amount of olive oil, and feed warm."
      }
    ],
    "imageUrl": ""
  },
  {
    "id": "sindirim_002",
    "title": {
      "tr": "Mis Kokulu Armutlu Yulaf Lapası",
      "en": "Pear and Oats"
    },
    "description": {
      "tr": "Armudun bağırsakları çalıştıran yapısı ve yulafın lif gücünün birleştiği sindirim dostu harika lapa.",
      "en": "A wonderful digestion-friendly porridge combining the bowel-stimulating nature of pear and fiber power of oats."
    },
    "category": 15,
    "ingredients": [
      {
        "amount": 1,
        "unit": {
          "tr": "adet",
          "en": "pcs"
        },
        "baseName": {
          "tr": "armut",
          "en": "pear"
        },
        "shoppingLabel": {
          "tr": "Armut",
          "en": "Pear"
        }
      },
      {
        "amount": 1,
        "unit": {
          "tr": "yemek kaşığı",
          "en": "tbsp"
        },
        "baseName": {
          "tr": "yulaf",
          "en": "oats"
        },
        "shoppingLabel": {
          "tr": "Yulaf",
          "en": "Oats"
        }
      }
    ],
    "preparationTime": 12,
    "calories": 110,
    "suitableAgeInMonths": 7,
    "allergicIngredients": [
      {
        "tr": "yulaf",
        "en": "oats"
      }
    ],
    "instructions": [
      {
        "tr": "Yulaf ununu suyla hafif hafif karıştırarak pişirelim, bebişimizin midelesine layık yumuşacık bir muhallebi kıvamı tutturalım.",
        "en": "Cook oat flour with water to make a pudding."
      },
      {
        "tr": "Vitaminleri kaçmasın diye cam rendeden geçirdiğimiz taze armudumuzu muhallebiye ekleyip sevgiyle karıştıralım. Ilık ılık servise hazır!",
        "en": "Add fresh pear passed through a glass grater, mix well, and serve warm."
      }
    ],
    "imageUrl": ""
  },
  {
    "id": "sindirim_003",
    "title": {
      "tr": "Şifa Deposu Anne Yoğurdu",
      "en": "Probiotic Yogurt"
    },
    "description": {
      "tr": "Bağırsak florasını güçlendiren yararlı bakteriler içeren, bebişlerin midesini rahatlatan ev yoğurdu.",
      "en": "Homemade yogurt containing beneficial bacteria to strengthen the bowel flora and soothe your baby's stomach."
    },
    "category": 15,
    "ingredients": [
      {
        "amount": 1,
        "unit": {
          "tr": "kase",
          "en": "bowl"
        },
        "baseName": {
          "tr": "ev yoğurdu",
          "en": "homemade yogurt"
        },
        "shoppingLabel": {
          "tr": "Yoğurt",
          "en": "Yogurt"
        }
      }
    ],
    "preparationTime": 5,
    "calories": 60,
    "suitableAgeInMonths": 6,
    "allergicIngredients": [
      {
        "tr": "süt",
        "en": "milk"
      }
    ],
    "instructions": [
      {
        "tr": "Sevgiyle mayaladığımız taptaze ev yoğurdunu dolaptan çıkarıp miniğimizin minik midesini üşütmemesi için oda sıcaklığına gelmesini bekleyelim.",
        "en": "Take fresh homemade yogurt from the fridge and let it come to room temperature."
      },
      {
        "tr": "Hiçbir şey eklemeden, en sade ve en doğal haliyle öğün aralarında kuzumuza kaşık kaşık yedirelim. Afiyet olsun!",
        "en": "Feed it plain, spoonful by spoonful, during your baby's snack times."
      }
    ],
    "imageUrl": ""
  },
  {
    "id": "sindirim_004",
    "title": {
      "tr": "Gaz Gideren Rahatlık Çayı",
      "en": "Fennel Tea (Baby)"
    },
    "description": {
      "tr": "Bebişinizin gaz sancılarını hafifletecek, mideyi rahatlatan rezene tohumu çayı.",
      "en": "Stomach-soothing fennel seed tea to help relieve your baby's painful gas cramps."
    },
    "category": 15,
    "ingredients": [
      {
        "amount": 0.5,
        "unit": {
          "tr": "tatlı kaşığı",
          "en": "tsp"
        },
        "baseName": {
          "tr": "rezene tohumu",
          "en": "fennel seeds"
        },
        "shoppingLabel": null
      }
    ],
    "preparationTime": 10,
    "calories": 0,
    "suitableAgeInMonths": 6,
    "allergicIngredients": [],
    "instructions": [
      {
        "tr": "Kokusuyla bile rahatlatan rezene tohumlarını sıcak suya bırakıp ağzını kapatalım ve 5 dakika demlenmeye bırakalım.",
        "en": "Steep fennel seeds in hot water with the lid closed for 5 minutes."
      },
      {
        "tr": "Temiz bir tülbent yardımıyla pürüzsüzce süzüp, çayımız ılındıktan sonra kuzumuzun gazını pışpışlamak için birkaç kaşıkçık içirelim.",
        "en": "Strain thoroughly through a cheesecloth, let it cool to warm, and give a few spoonfuls to your baby."
      }
    ],
    "imageUrl": ""
  },
  {
    "id": "sindirim_005",
    "title": {
      "tr": "Mide Dostu Elma Suyu",
      "en": "Boiled Apple Juice"
    },
    "description": {
      "tr": "Mide bulantısını yatıştıran ve sindirimi destekleyen, haşlanmış elmanın süzülmüş şifalı suyu.",
      "en": "A healing strained juice of boiled apple to soothe nausea and support healthy digestion."
    },
    "category": 15,
    "ingredients": [
      {
        "amount": 1,
        "unit": {
          "tr": "adet",
          "en": "pcs"
        },
        "baseName": {
          "tr": "elma",
          "en": "apple"
        },
        "shoppingLabel": {
          "tr": "Elma",
          "en": "Apple"
        }
      }
    ],
    "preparationTime": 15,
    "calories": 30,
    "suitableAgeInMonths": 6,
    "allergicIngredients": [],
    "instructions": [
      {
        "tr": "Güzelce yıkadığımız elmayı temiz suda mis gibi yumuşayana kadar tatlı tatlı haşlayalım.",
        "en": "Boil the apple in clean water until soft."
      },
      {
        "tr": "Şifalı haşlama suyunu incecik bir süzgeçten süzüp, bebişimizin midesini rahatlatması için ılık bir şekilde içirelim.",
        "en": "Strain the cooking water through a fine sieve and serve warm for your baby to drink."
      }
    ],
    "imageUrl": ""
  },
  {
    "id": "sindirim_006",
    "title": {
      "tr": "Mürdüm Erikli Mutlu Bağırsak Püresi",
      "en": "Plum and Pear Mix"
    },
    "description": {
      "tr": "Kabızlık dönemlerinde bebişinizin imdadına yetişecek, armut ve mürdüm eriği püresi.",
      "en": "Pear and damson plum puree to rescue your baby during constipation periods."
    },
    "category": 15,
    "ingredients": [
      {
        "amount": 1,
        "unit": {
          "tr": "adet",
          "en": "pcs"
        },
        "baseName": {
          "tr": "mürdüm eriği",
          "en": "plum"
        },
        "shoppingLabel": {
          "tr": "Erik",
          "en": "Plum"
        }
      },
      {
        "amount": 1,
        "unit": {
          "tr": "adet",
          "en": "pcs"
        },
        "baseName": {
          "tr": "armut",
          "en": "pear"
        },
        "shoppingLabel": {
          "tr": "Armut",
          "en": "Pear"
        }
      }
    ],
    "preparationTime": 12,
    "calories": 70,
    "suitableAgeInMonths": 7,
    "allergicIngredients": [],
    "instructions": [
      {
        "tr": "Şifa deposu mürdüm eriğimizi ve sulu armudumuzu yıkayıp, buharda yumuşacık olana kadar bir güzel pişirelim.",
        "en": "Wash and steam damson plum and pear until tender."
      },
      {
        "tr": "Meyvelerimizi çatalla hafifçe ezerek tam miniğimize layık, ipeksi bir püre kıvamında yedirelim.",
        "en": "Mash the fruits with a fork and feed in a puree consistency."
      }
    ],
    "imageUrl": ""
  },
  {
    "id": "sindirim_007",
    "title": {
      "tr": "Zeytinyağlı Yumuşacık Bamya Püresi",
      "en": "Okra with Olive Oil"
    },
    "description": {
      "tr": "Lifli yapısıyla dışkılamayı kolaylaştıran, zeytinyağı ile zenginleştirilmiş yumuşak bamya püresi.",
      "en": "A soft okra puree enriched with olive oil, making bowel movements easier with its fibrous texture."
    },
    "category": 15,
    "ingredients": [
      {
        "amount": 5,
        "unit": {
          "tr": "adet",
          "en": "pcs"
        },
        "baseName": {
          "tr": "bamya",
          "en": "okra"
        },
        "shoppingLabel": {
          "tr": "Bamya",
          "en": "Okra"
        }
      }
    ],
    "preparationTime": 20,
    "calories": 40,
    "suitableAgeInMonths": 9,
    "allergicIngredients": [],
    "instructions": [
      {
        "tr": "Bamyalarımızı güzelce haşlayalım, miniğimizin boğazına takılmaması için çekirdekli kısımlarını süzgeçle özenle ayıralım.",
        "en": "Boil okras and strain through a sieve to remove the seeds."
      },
      {
        "tr": "Elde ettiğimiz o yumuşacık bamya özüne mis gibi sızma zeytinyağı ekleyip lezzetlendirerek püre halinde yedirelim.",
        "en": "Add extra virgin olive oil to the resulting okra pulp and feed as a puree."
      }
    ],
    "imageUrl": ""
  },
  {
    "id": "sindirim_008",
    "title": {
      "tr": "Bağışıklık Dostu Ev Yapımı Kefir",
      "en": "Kefir (Homemade)"
    },
    "description": {
      "tr": "Probiyotik gücü yoğurttan kat kat yüksek olan, bebişinizin bağışıklığını ve sindirimini coşturacak ev yapımı kefir.",
      "en": "Homemade kefir, with probiotic power many times higher than yogurt, to boost your baby's immunity and digestion."
    },
    "category": 15,
    "ingredients": [
      {
        "amount": 0.5,
        "unit": {
          "tr": "çay bardağı",
          "en": "cup"
        },
        "baseName": {
          "tr": "ev yapımı kefir",
          "en": "homemade kefir"
        },
        "shoppingLabel": {
          "tr": "Kefir",
          "en": "Kefir"
        }
      }
    ],
    "preparationTime": 2,
    "calories": 50,
    "suitableAgeInMonths": 10,
    "allergicIngredients": [
      {
        "tr": "süt",
        "en": "milk"
      }
    ],
    "instructions": [
      {
        "tr": "Doğal kefir mayasıyla binbir emek mayaladığımız şifa kaynağı kefirimizi dolaptan çıkarıp oda sıcaklığına getirelim.",
        "en": "Take homemade kefir fermented with kefir grains from the fridge."
      },
      {
        "tr": "Miniğimizin minik bağırsakları yavaş yavaş alışsın diye başlangıçta günde 1-2 tatlı kaşıkçık vererek başlayalım.",
        "en": "Start by giving 1-2 teaspoons a day to let your baby get used to it."
      }
    ],
    "imageUrl": ""
  },
  {
    "id": "sindirim_009",
    "title": {
      "tr": "İshal Kurtarıcı Geleneksel Pirinç Suyu",
      "en": "Rice Water (For Diarrhea)"
    },
    "description": {
      "tr": "Bebişiniz ishal olduğunda mideyi toparlayacak ve sıvı kaybını önleyecek geleneksel pirinç suyu.",
      "en": "Traditional rice water to settle the stomach and prevent dehydration when your baby has diarrhea."
    },
    "category": 15,
    "ingredients": [
      {
        "amount": 2,
        "unit": {
          "tr": "yemek kaşığı",
          "en": "tbsp"
        },
        "baseName": {
          "tr": "pirinç",
          "en": "rice"
        },
        "shoppingLabel": {
          "tr": "Pirinç",
          "en": "Rice"
        }
      }
    ],
    "preparationTime": 20,
    "calories": 20,
    "suitableAgeInMonths": 6,
    "allergicIngredients": [],
    "instructions": [
      {
        "tr": "Pirincimizi bol temiz suda, pirinç taneleri iyice ezilip tüm şifasını suya bırakana kadar uzun uzun, güzelce haşlayalım.",
        "en": "Boil rice in plenty of clean water for a long time until the grains are completely soft and mushy."
      },
      {
        "tr": "Haşlanan o nişastalı şifa suyunu süzüp biraz ılındırdıktan sonra, kaşıkla miniğimize yudum yudum içirip midesini sarmalayalım.",
        "en": "Strain the rice water, let it cool to warm, and feed it to your baby with a spoon."
      }
    ],
    "imageUrl": ""
  },
  {
    "id": "sindirim_010",
    "title": {
      "tr": "Mideyi Toparlayan Patates ve Havuç Lapası",
      "en": "Potato and Carrot Porridge"
    },
    "description": {
      "tr": "Yağsız haşlanmış patates ve havucun mideyi yormayan ve bağırsakları toparlayan şifalı lapası.",
      "en": "A healing porridge of fat-free boiled potato and carrot to settle the stomach and firm up the bowels."
    },
    "category": 15,
    "ingredients": [
      {
        "amount": 1,
        "unit": {
          "tr": "adet",
          "en": "pcs"
        },
        "baseName": {
          "tr": "patates",
          "en": "potato"
        },
        "shoppingLabel": {
          "tr": "Patates",
          "en": "Potato"
        }
      },
      {
        "amount": 0.5,
        "unit": {
          "tr": "adet",
          "en": "pcs"
        },
        "baseName": {
          "tr": "havuç",
          "en": "carrot"
        },
        "shoppingLabel": {
          "tr": "Havuç",
          "en": "Carrot"
        }
      }
    ],
    "preparationTime": 20,
    "calories": 95,
    "suitableAgeInMonths": 7,
    "allergicIngredients": [],
    "instructions": [
      {
        "tr": "Miniğimizin hassas bağırsaklarını yormamak için patates ve havucu hiç yağ eklemeden, temiz suda yumuşacık olana kadar haşlayalım.",
        "en": "Boil potato and carrot in clean water without adding any fat until tender."
      },
      {
        "tr": "Haşlanan sebzelerimizi süzüp pürüzsüz bir kıvam alana kadar çatalla sevgiyle ezelim ve kuzumuza afiyetle yedirelim.",
        "en": "Drain the vegetables, mash them with a fork until smooth, and feed."
      }
    ],
    "imageUrl": ""
  }
]
